rcdl/__init__.py
rcdl/__main__.py
rcdl/utils.py
rcdl/core/api.py
rcdl/core/config.py
rcdl/core/db.py
rcdl/core/db_queries.py
rcdl/core/downloader.py
rcdl/core/downloader_subprocess.py
rcdl/core/file_io.py
rcdl/core/fuse.py
rcdl/core/models.py
rcdl/core/parser.py
rcdl/interface/cli.py
rcdl/interface/ui.py
rcdl/scripts/migrate_1_to_2.py
rcdl/scripts/migrate_creators_json_txt.py
rcdl/scripts/migrate_old_format_to_db.py
rcdl/scripts/upload_pypi.py
rcdl-2.2.8.dist-info/entry_points.txt
rcdl-2.2.8.dist-info/WHEEL
rcdl-2.2.8.dist-info/METADATA
rcdl-2.2.8.dist-info/RECORD
