Metadata-Version: 2.4
Name: rcdl
Version: 2.2.8
Summary: Coomer/Kemono CLI Downloader
Keywords: downloader,video,media
Author: Anonymous
Requires-Python: >=3.12
Classifier: Programming Language :: Python :: 3
Classifier: License :: OSI Approved :: MIT License
Classifier: Operating System :: OS Independent
Requires-Dist: click>=8.2
Requires-Dist: requests>=2.32
Requires-Dist: pathvalidate==3.3.1
Requires-Dist: moviepy==2.2.1
Requires-Dist: rich==14.2.0
